{
    "version": "3.7.4",
    "description": "A HTTP inspection tool with support for HTTP/2 and HTTP/3.",
    "homepage": "https://pororoca.io",
    "license": "Freeware",
    "notes": "HTTP/3 (QUIC) support requires Windows Server 2022, Windows 11 or later.",
    "architecture": {
        "64bit": {
            "url": "https://github.com/alexandrehtrb/Pororoca/releases/download/3.7.4/Pororoca_3.7.4_win-x64_portable.zip",
            "hash": "6fe82775cda85a071ccb0deecb143388bc361ca8dfea33bd661c613730286d89"
        },
        "32bit": {
            "url": "https://github.com/alexandrehtrb/Pororoca/releases/download/3.7.4/Pororoca_3.7.4_win-x86_portable.zip",
            "hash": "412365dc8b4c8ae9fc92e159cfacfcef6d19ffe2b7d41829cf41c2df62f15bd5"
        }
    },
    "bin": "Pororoca.exe",
    "shortcuts": [
        [
            "Pororoca.exe",
            "Pororoca"
        ]
    ],
    "persist": "PororocaUserData",
    "checkver": {
        "github": "https://github.com/alexandrehtrb/Pororoca"
    },
    "autoupdate": {
        "architecture": {
            "64bit": {
                "url": "https://github.com/alexandrehtrb/Pororoca/releases/download/$version/Pororoca_$majorVersion.$minorVersion.$patchVersion_win-x64_portable.zip"
            },
            "32bit": {
                "url": "https://github.com/alexandrehtrb/Pororoca/releases/download/$version/Pororoca_$majorVersion.$minorVersion.$patchVersion_win-x86_portable.zip"
            }
        }
    }
}
